{
	"topList": [
	  {
		"imgUrl": "images/top01.jpg",
		"disc": "【头条】专家称稳房价能取得一定成绩 7.2亿存量房数据不可怕"
	  },
	  {
		"imgUrl": "images/top02.jpg",
		"disc": "【头条】深圳楼市八成人此时不愿买房 住宅降温写字楼火热"
	  },
	  {
		"imgUrl": "images/top03.jpg",
		"disc": "【头条】深圳等一线城市 地产投机炒作影响全国去库存"
	  },
	  {
		"imgUrl": "images/top04.jpg",
		"disc": "【头条】你能买得起房了吗？ 深圳上海多地出台楼市新规"
	  }
	],
  "articleList": [
	{
	  "id": "001",
      "createDate": "2016-02-01",
	  "imgUrl": "images/CvtcKVb4kCOAFPSJAABoTj3yFyg652.jpg",
	  "title": "一二线城市楼市疯狂 深圳房价已出现小幅回调",
	  "abstract": "中国一二线楼市仍然处于“亢奋”状态：上周多地新房成交维持高位，二手房成交再创新高，而且市场热度突破了一二线的范围，开始带动全国大中城市的房地产市场整体升温。但与此同时，一些地方房地产市场已悄然出现“乏力”和“退烧”的信号。"
	},
	{
	  "id": "002",
      "createDate": "2016-02-02",
	  "imgUrl": "images/CvtcKVb4i_CAISehAAA5OKxLGOk688.jpg",
	  "title": "小Q早报：中介乱象干扰楼市预期",
	  "abstract": "二手房交易，大多通过中介完成。据住建部统计，我国目前大概有6万多家房地产中介机构。这些机构对促进房地产交易发挥了积极作用。但是，一些不良房地产中介机构，通过各种方式谋取不正当利益，扰乱市场秩序，坑害消费者权益。"
	},
	{
	  "id": "003",
      "createDate": "2016-02-02",
	  "imgUrl": "images/CvtcKlb0nPmAI_7zAAA7VZUpHmI058.jpg",
	  "title": "上海深圳楼市调控紧锣密鼓 深圳全面收紧房贷审核",
	  "abstract": "密集调研及部署之后，上海房地产调控新政即将落地。上海市政府今日召开新闻发布会，由市住房城乡建设委、市工商局、市金融办等部门共同参加，重点介绍上海市促进房地产平稳健康发展的相关举措。而在此之前，深圳经济特区金融学会3月23日亦发文全面收紧房贷审核。"
	},
	{
	  "id": "004",
      "createDate": "2016-02-03",
	  "imgUrl": "images/CvtcKlb0mLGAInn2AABbpJLYo6Q485.jpg",
	  "title": "楼市三大“热词”受关注 变味加杠杆引发泡沫",
	  "abstract": "正在此间举行的博鳌亚洲论坛2016年年会上，杠杆、库存、税改是关于楼市话题的三大“热词”。一旦房地产市场下滑太多，部分地方政府的财政将难以为继，银行体系的安全也会受到挑战。"
	},
	{
	  "id": "005",
      "createDate": "2016-02-03",
	  "imgUrl": "images/CvtcKVbzii-AeWnhAAB7qEZ4OCA808.png",
	  "title": "政策严控深圳房价要降？专家：不可能大幅走低",
	  "abstract": "先是打击“首付贷”，后是禁止“众筹炒房”，此前领涨全国的深圳楼市，3月开始有些变化。近日，有传言称深圳某些片区出现了楼盘降价销售，以及投资客大批量抛售房产的现象。对此，记者展开了调查。"
	},
	{
	  "id": "006",
      "createDate": "2016-02-05",
	  "imgUrl": "images/CvtcKlbzSAKAP39XAAaY36XR3qQ069.png",
	  "title": "深圳房价崩盘是一种怎样的体验？",
	  "abstract": "2007年中，深圳商品房均价曾经攀升至18000元/平方米，达到全国最高水平；2008年，深圳市一手住宅成交均价12800元/平方米，同比下跌4.4%，不少楼盘价格跌幅甚至达到50%；"
	},
	{
	  "id": "007",
      "createDate": "2016-02-08",
	  "imgUrl": "images/CvtcKVbx_VWAfZi4AABKJW0T01Q193.jpg",
	  "title": "万万没想到！ 涨房租的都是良心好房东",
	  "abstract": "深圳房价暴涨50%，于是涨房租成了对楼市最起码的尊重。数据显示，深圳2016年以来全市套均租金为5567元，平均租金为74.7元/平。"
	},
	{
	  "id": "008",
      "createDate": "2016-02-08",
	  "imgUrl": "images/CvtcKlbx95OAN9G4AABddotHclo045.jpg",
	  "title": "深圳楼市并未大范围降价 观望情绪浓楼市趋于冷淡",
	  "abstract": "“投资客降200万抛售豪宅”、“房价真正拐点即将到来”……这段时间，有关深圳楼市降温的讨论，俨然成为各大机构、网友、市场讨论最为炙热的话题。"
	},
	{
	  "id": "009",
      "createDate": "2016-02-11",
	  "imgUrl": "images/CvtcKlbx95OAN9G4AABddotHclo045.jpg",
	  "title": "深圳楼市并未大范围降价 观望情绪浓楼市趋于冷淡",
	  "abstract": "“投资客降200万抛售豪宅”、“房价真正拐点即将到来”……这段时间，有关深圳楼市降温的讨论，俨然成为各大机构、网友、市场讨论最为炙热的话题。"
	},
	{
	  "id": "010",
      "createDate": "2016-02-11",
	  "imgUrl": "images/CvtcKlbw-xeAOjcBAABOMq8_zmo716.jpg",
	  "title": "为什么要买房？看完这篇你就懂了",
	  "abstract": "近日，央视财经频道发布一组现场调查数据称，我国在过去15年里，房价增长了300倍。结论一出，立即引发各方热议，有人指出，300倍这个数字有些言过其实，也有人表示，尽管300倍可能不符合现实，但确实表达出了不少人对当下高房价的吐槽之心。"
	},
	{
	  "id": "011", "createDate": "2016-02-15",
	  "imgUrl": "images/CvtcKlbw47OAJM5_AABrDcWjTbc087.jpg",
	  "title": "地产三大亨：6大因素致2016房价暴跌",
	  "abstract": "虽然央行降息降准利好房地产市场，但地产三大亨牛刀、王健林、任志强却一致认为2016年的房价会暴跌。小编看到此消息为之一震，为何地产大亨会如此判断？我们从6大因素来看看，会不会导致2016房价暴跌。"
	},
	{
	  "id": "012",
      "createDate": "2016-02-16",
	  "imgUrl": "images/CvtcKVbwvuuAHxuvAAA7M3Wo7is178.jpg",
	  "title": "杠杆收缩深圳楼市 投资客开始抛盘",
	  "abstract": "记者从深圳不愿具名的机构高层处获悉，近日深圳投资客开始抛售楼盘，部分一手楼盘也以低开方式入市，深圳楼市春节之后出现了与2015年不一样的变化。"
	},
	{
	  "id": "013",
      "createDate": "2016-02-16",
	  "imgUrl": "images/CvtcKVbvYkyAaiIKAACHtC7E5g8875.jpg",
	  "title": "深圳人竟买下了0.6个东莞 部分莞人疾呼限购",
	  "abstract": "东莞和深圳，这两个巨大的新兴城市，像盛放众生感情的容器，一个在北，一个在南，既清晰又暧昧，其内在联系和情感纠葛的复杂程度远远超过人们的想象。"
	},
	{
	  "id": "014",
      "createDate": "2016-02-17",
	  "imgUrl": "images/CvtcKVbvVsKAZf_-AABZXQ96_OU874.jpg",
	  "title": "深圳房价那么高 我们还能买到哪里的房子？",
	  "abstract": "深圳的房价在去年涨出了新高度，在今年也没少吸引大众的目光。如果要问深圳的房价究竟有多高？日前的“深圳一小区抵得上中国第五大机场”的消息已经给出了答案。"
	},
	{
	  "id": "015",
      "createDate": "2016-02-17",
	  "imgUrl": "images/CvtcKlbvUiCAA61_AAAmP0KrX28581.jpg",
	  "title": "深圳楼市调控加码现降温现象 短炒投资客抛盘套现",
	  "abstract": "疯狂之后，回归理性。深圳楼市出现了降温现象。国家统计局数据显示，截至2016年2月，深圳新建商品住宅"
	},
	{
	  "id": "016",
      "createDate": "2016-02-19",
	  "imgUrl": "images/CvtcKVbrZ96ATs3ZAAAZH9QA9Vk966.jpg",
	  "title": "从交首付到拿钥匙 买新房还要交哪些费用？",
	  "abstract": "买套新房子，可不是交完首付就完事儿了。从交首付到拿钥匙，首付之外的费用也是一笔不小的支出。很多朋友经常通过各种渠道问询首付之外的一些费用到底有哪些，要准备多少钱。今天我们就来梳理下买新房除了首付还需要交哪些钱。"
	},
	{
	  "id": "017",
      "createDate": "2016-02-19",
	  "imgUrl": "images/CvtcKVb4kCOAFPSJAABoTj3yFyg652.jpg",
	  "title": "买套新房子，可不是交完首付就完事儿了。从交首付到拿钥匙，首付之外的费用也是一笔不小的支出。很多朋友经常通过各种渠道问询首付之外的一些费用到底有哪些，要准备多少钱。今天我们就来梳理下买新房除了首付还需要交哪些钱。",
	  "abstract": "买套新房子，可不是交完首付就完事儿了。从交首付到拿钥匙，首付之外的费用也是一笔不小的支出。很多朋友经常通过各种渠道问询首付之外的一些费用到底有哪些，要准备多少钱。今天我们就来梳理下买新房除了首付还需要交哪些钱。"
	},
	{
	  "id": "018",
      "createDate": "2016-02-19",
	  "imgUrl": "images/CvtcKlbrYBuAOToEAAAeIqT7f1o819.jpg",
	  "title": "如何选择适合自己的户型？12星座户型选择指南",
	  "abstract": "拥有一个属于自己的房子，是大部分人的梦想，但购买一个令人满意的房子却是一件让人很头疼的事。在挑选房子时，每个人都有着自己的要求，而不同性格的人对房子有着不同的喜好。你是否也在为选择什么样的户型所苦恼呢？"
	},
	{
	  "id": "019",
      "createDate": "2016-02-19",
	  "imgUrl": "images/CvtcKlbrW8CAE8F4AABTypXZ--8253.jpg",
	  "title": "当心陷二手房定金雷区 3招教你如何防雷",
	  "abstract": "现在一些城市的二手房交易市场非常火热，很多人都是通过卖房来换房。例如在北京，很多二手房比新房贵，如果卖房人其意向中的房子涨价了，则其也会提高现有的想要卖掉的房屋的价格。"
	},
	{
	  "id": "020",
      "createDate": "2016-02-20",
	  "imgUrl": "images/CvtcKlbqIV-AREBuAAAwoIvRpYc922.jpg",
	  "title": "楼市\"高烧\"地市冷 2月全国土地交易持续下行",
	  "abstract": "2016年2月，全国多地楼市成交持续火爆。但相对于“高烧”的楼市，土地市场却显得”冷清“了许多。据中国指数研究院数据显示，2016年2月，全国土地市场交易呈现出”量跌价涨“的态势。"
	}
  ]
}
